rss_reader/__init__.py
rss_reader/check_functions.py
rss_reader/main_functions.py
rss_reader/rss_reader.py
rss_reader/testing_module.py
rss_reader_by_Coromilly-2.21.dist-info/METADATA
rss_reader_by_Coromilly-2.21.dist-info/WHEEL
rss_reader_by_Coromilly-2.21.dist-info/entry_points.txt
rss_reader_by_Coromilly-2.21.dist-info/top_level.txt
rss_reader_by_Coromilly-2.21.dist-info/RECORD
