Metadata-Version: 2.1
Name: rss-reader-by-Coromilly
Version: 2.21
Summary: Pure Python command-line RSS reader
Home-page: https://github.com/Coromilly/epam-q4-2019/tree/project
Author: Aleksandr_Levdansky
Author-email: coromilly@gmail.com
License: UNKNOWN
Platform: UNKNOWN
Classifier: Programming Language :: Python :: 3.8
Classifier: Operating System :: OS Independent
Requires-Python: >=3.7
Requires-Dist: beautifulsoup4
Requires-Dist: feedparser
Requires-Dist: requests
